mbpls/__init__.py
mbpls/mbpls.py
mbpls/data/__init__.py
mbpls/data/get_data.py
mbpls/tests/__init__.py
mbpls/tests/load_data.py
mbpls/tests/test_Installation.py
mbpls/tests/test_mbpls.py
mbpls-1.0.4.dist-info/LICENSE.txt
mbpls-1.0.4.dist-info/METADATA
mbpls-1.0.4.dist-info/WHEEL
mbpls-1.0.4.dist-info/top_level.txt
mbpls-1.0.4.dist-info/RECORD
