Metadata-Version: 2.1
Name: mbpls
Version: 1.0.4
Summary: An implementation of the most common partial least squares algorithms as multi-block methods
Home-page: https://github.com/DTUComputeStatisticsAndDataAnalysis/MBPLS
Author: Andreas Baum, Laurent Vermue
Author-email: <andba@dtu.dk>, <lauve@dtu.dk>
License: new BSD
Platform: UNKNOWN
Classifier: Intended Audience :: Science/Research
Classifier: Intended Audience :: Developers
Classifier: License :: OSI Approved
Classifier: Programming Language :: Python
Classifier: Topic :: Software Development
Classifier: Topic :: Scientific/Engineering
Classifier: Operating System :: Microsoft :: Windows
Classifier: Operating System :: POSIX
Classifier: Operating System :: Unix
Classifier: Operating System :: MacOS
Classifier: Programming Language :: Python :: 3.5
Classifier: Programming Language :: Python :: 3.6
Classifier: Programming Language :: Python :: 3.7
Classifier: Development Status :: 5 - Production/Stable
Requires-Python: >=3.5
Requires-Dist: numpy (>=1.13.3)
Requires-Dist: scipy (>=1.0.0)
Requires-Dist: scikit-learn (>=0.22.1)
Requires-Dist: pandas (>=0.20.0)
Provides-Extra: docs
Requires-Dist: sphinx (>=1.6); extra == 'docs'
Requires-Dist: sphinx-rtd-theme; extra == 'docs'
Requires-Dist: nbsphinx; extra == 'docs'
Requires-Dist: nbsphinx-link; extra == 'docs'
Provides-Extra: extras
Requires-Dist: matplotlib; extra == 'extras'
Provides-Extra: tests
Requires-Dist: pytest; extra == 'tests'
